odoo10_addon_analytic_base_department-10.0.1.0.0-py2.7-nspkg.pth
odoo/addons/analytic_base_department/LICENSE
odoo/addons/analytic_base_department/README.rst
odoo/addons/analytic_base_department/__init__.py
odoo/addons/analytic_base_department/__manifest__.py
odoo/addons/analytic_base_department/i18n/analytic_base_department.pot
odoo/addons/analytic_base_department/i18n/es.po
odoo/addons/analytic_base_department/i18n/pt.po
odoo/addons/analytic_base_department/models/__init__.py
odoo/addons/analytic_base_department/models/analytic.py
odoo/addons/analytic_base_department/tests/__init__.py
odoo/addons/analytic_base_department/tests/test_line_department.py
odoo/addons/analytic_base_department/views/analytic.xml
odoo10_addon_analytic_base_department-10.0.1.0.0.dist-info/DESCRIPTION.rst
odoo10_addon_analytic_base_department-10.0.1.0.0.dist-info/METADATA
odoo10_addon_analytic_base_department-10.0.1.0.0.dist-info/RECORD
odoo10_addon_analytic_base_department-10.0.1.0.0.dist-info/WHEEL
odoo10_addon_analytic_base_department-10.0.1.0.0.dist-info/metadata.json
odoo10_addon_analytic_base_department-10.0.1.0.0.dist-info/namespace_packages.txt
odoo10_addon_analytic_base_department-10.0.1.0.0.dist-info/top_level.txt
